{
    "Welcome to My Shopping List App": "Welcome to My Shopping List App",
    "Go To Shopping Lists": "Go To Shopping Lists",
    "Add New List": "Add New List",
    "Delete": "Delete",
    "Archive": "Archive",
    "Confirm Delete?": "Confirm Delete?",
    "Yes": "Yes",
    "No": "No",
    "Go to Homepage": "Go to Homepage",
    "Add Item": "Add Item",
    "Show Done Items": "Show Done Items",
    "Hide Done Items": "Hide Done Items",
    "Back to Shopping Lists": "Back to Shopping Lists",
    "Add Items to List": "Add Items to List",
    "Switch to Light Mode": "Switch to Light Mode",
    "Light Mode": "Light Mode",
    "Dark Mode": "Dark Mode",
    "Archived Lists": "Archived Lists",
    "Active Lists": "Active Lists",
    "Shopping Lists": "Shopping Lists"
  }
  